kharser/__init__.py
kharser/freeipa.py
kharser/pattern.py
kharser-0.1.1.dist-info/WHEEL
kharser-0.1.1.dist-info/METADATA
kharser-0.1.1.dist-info/RECORD
