Metadata-Version: 2.1
Name: kharser
Version: 0.1.1
Summary: parse stuff
Author: KhalidCK
Author-email: fr.ckhalid@gmail.com
Requires-Python: >=3.7,<4.0
Classifier: Programming Language :: Python :: 3
Classifier: Programming Language :: Python :: 3.7
Classifier: Programming Language :: Python :: 3.8
